MANIFEST.in
README.txt
setup.py
XStatic_BootstrapOverflowNavs.egg-info/PKG-INFO
XStatic_BootstrapOverflowNavs.egg-info/SOURCES.txt
XStatic_BootstrapOverflowNavs.egg-info/dependency_links.txt
XStatic_BootstrapOverflowNavs.egg-info/namespace_packages.txt
XStatic_BootstrapOverflowNavs.egg-info/not-zip-safe
XStatic_BootstrapOverflowNavs.egg-info/top_level.txt
xstatic/__init__.py
xstatic/pkg/__init__.py
xstatic/pkg/bootstrapoverflownavs/__init__.py
xstatic/pkg/bootstrapoverflownavs/data/overflow-nav.js