Metadata-Version: 1.0
Name: XStatic-BootstrapOverflowNavs
Version: 1.1
Summary: BootstrapOverflowNavs 1 (XStatic packaging standard)
Home-page: https://github.com/tomiford/bootstrap-overflow-navs
Author: Yask Srivastava
Author-email: yask123@gmail.com
License: (same as BootstrapOverflowNavs)
Keywords: bootstrapoverflownavs xstatic
Platform: any
